memorizesrs.py
memorizesrs-1.0.1.dist-info/METADATA
memorizesrs-1.0.1.dist-info/WHEEL
memorizesrs-1.0.1.dist-info/top_level.txt
memorizesrs-1.0.1.dist-info/zip-safe
memorizesrs-1.0.1.dist-info/RECORD
